everything/__init__.py
everything/__main__.py
everything/generator.py
everything/utils/openai.py
everything/utils/scanner.py
dothething-0.1.2.dist-info/LICENSE.txt
dothething-0.1.2.dist-info/METADATA
dothething-0.1.2.dist-info/WHEEL
dothething-0.1.2.dist-info/entry_points.txt
dothething-0.1.2.dist-info/RECORD
