Metadata-Version: 2.1
Name: dothething
Version: 0.1.2
Summary: from everything import anything
License: MIT
Author: Wolf Mermelstein
Author-email: wolfmermelstein@gmail.com
Requires-Python: >=3.11,<4.0
Classifier: License :: OSI Approved :: MIT License
Classifier: Programming Language :: Python :: 3
Classifier: Programming Language :: Python :: 3.11
Classifier: Programming Language :: Python :: 3.12
Requires-Dist: black (>=24.4.2,<25.0.0)
Requires-Dist: click (>=8.1.7,<9.0.0)
Requires-Dist: openai (>=1.35.9,<2.0.0)
Requires-Dist: pylint (>=3.2.5,<4.0.0)
Requires-Dist: typing-extensions (>=4.12.2,<5.0.0)
